{
  "id": "camel-archer-3",
  "baseId": "camel-archer",
  "type": "unit",
  "name": "Camel Archer",
  "age": 3,
  "civs": [
    "ab"
  ],
  "description": "Highly mobile and durable ranged unit effective against all cavalry.\n\n+Bonus damage vs spearmen\n\n+Causes enemy cavalry to deal less damage\n\n-High cost",
  "classes": [
    "Light Ranged Cavalry",
    "Camel"
  ],
  "unique": true,
  "costs": {
    "food": 180,
    "wood": 60,
    "stone": 0,
    "gold": 0,
    "total": 240,
    "popcap": 1,
    "time": 35
  },
  "producedBy": [
    "archery-range"
  ],
  "hitpoints": 210,
  "movement": {
    "speed": 1.63
  },
  "weapons": [
    {
      "type": "ranged",
      "damage": 12,
      "speed": 1.25,
      "range": {
        "min": 0,
        "max": 3.8
      }
    }
  ],
  "armor": [],
  "sight": {
    "line": 38,
    "height": 10
  },
  "icon": "https://data.aoe4world.com/images/units/camel-archer-3.png"
}