{
  "id": "sanctity-2",
  "baseId": "sanctity",
  "type": "technology",
  "name": "Sanctity",
  "pbgid": 181960,
  "attribName": "upgrade_unit_religious_sanctity_4_sul",
  "age": 2,
  "civs": [
    "de"
  ],
  "description": "Allow Scholars to capture Sacred Sites before the Castle Age (III). Sacred Sites generate +50% more Gold.",
  "classes": [
    "religious",
    "technology"
  ],
  "displayClasses": [
    "Religious Technology"
  ],
  "unique": true,
  "costs": {
    "food": 0,
    "wood": 0,
    "stone": 0,
    "gold": 0,
    "total": 0,
    "popcap": 0,
    "time": 210
  },
  "producedBy": [
    "mosque",
    "dome-of-the-faith"
  ],
  "icon": "https://data.aoe4world.com/images/technologies/sanctity-2.png",
  "effects": [
    {
      "property": "goldGeneration",
      "select": {
        "id": [
          "sacred-site"
        ]
      },
      "effect": "multiply",
      "value": 1.5,
      "type": "passive"
    },
    {
      "property": "unknown",
      "select": {
        "id": [
          "scholar"
        ]
      },
      "effect": "multiply",
      "value": 1,
      "type": "ability"
    }
  ]
}