{
  "id": "wedge-rivets-3-delhi",
  "baseId": "wedge-rivets",
  "type": "technology",
  "name": "Wedge Rivets",
  "age": 3,
  "civs": [
    "de"
  ],
  "description": "Increase the ranged armor of all non-siege units by +1.",
  "classes": [
    "ranged",
    "armor",
    "technology"
  ],
  "displayClasses": [
    "Ranged Armor Technology 2/3"
  ],
  "unique": true,
  "costs": {
    "food": 0,
    "wood": 0,
    "stone": 0,
    "gold": 0,
    "total": 0,
    "popcap": 0,
    "time": 300
  },
  "producedBy": [
    "blacksmith"
  ],
  "icon": "https://data.aoe4world.com/images/technologies/wedge-rivets.png",
  "effects": [
    {
      "property": "rangedArmor",
      "select": {
        "class": [
          [
            "infantry"
          ],
          [
            "cavalry"
          ]
        ]
      },
      "effect": "change",
      "value": 1,
      "type": "passive"
    }
  ]
}