{
  "id": "town-center-2",
  "baseId": "town-center",
  "type": "building",
  "name": "Town Center",
  "pbgid": 6034931,
  "attribName": "building_town_center_chi_ha_01",
  "age": 2,
  "civs": [
    "zx"
  ],
  "description": "All Resources can be dropped off here. Produces Villagers, Scouts, Officials, and increases your maximum Population. Adds additional attacks while garrisoned.\nNon-Capital Town Centers can't detect stealth or disguises.",
  "classes": [
    "building",
    "emits_herding_interest",
    "has_default_building_weapons",
    "hq",
    "land_food_deposit_4_by_4",
    "production_building",
    "resource_drop_off",
    "siegeable",
    "town_bell_target",
    "town_center",
    "town_center_non_capital"
  ],
  "displayClasses": [
    "Economy & Population Building"
  ],
  "unique": false,
  "costs": {
    "food": 0,
    "wood": 400,
    "stone": 350,
    "gold": 0,
    "vizier": 0,
    "oliveoil": 0,
    "total": 750,
    "popcap": 0,
    "time": 150
  },
  "producedBy": [
    "villager"
  ],
  "icon": "https://data.aoe4world.com/images/buildings/town-center-2.png",
  "hitpoints": 2500,
  "weapons": [],
  "armor": [
    {
      "type": "ranged",
      "value": 50
    }
  ],
  "sight": {
    "inner_height": 501,
    "inner_radius": 28,
    "outer_height": -15,
    "outer_radius": 52,
    "base": 51.30232558139535,
    "line": 52,
    "height": 501
  },
  "garrison": {
    "capacity": 8,
    "classes": [
      "villager",
      "infantry",
      "monk",
      "cavalry",
      "infantry ranged",
      "khan"
    ]
  },
  "influences": []
}