{
  "__note__": "This is file is autogenerated, do not edit it manually. For more info https://data.aoe4world.com/",
  "__version__": "0.0.2",
  "id": "teak-masts",
  "name": "Teak Masts",
  "type": "technology",
  "civs": [
    "ab",
    "ay"
  ],
  "unique": true,
  "displayClasses": [
    "Naval Technology"
  ],
  "classes": [
    "naval",
    "technology"
  ],
  "minAge": 2,
  "icon": "https://data.aoe4world.com/images/technologies/teak-masts-2.png",
  "description": "Increase the health of military ships by +10%.",
  "variations": [
    {
      "id": "teak-masts-3",
      "baseId": "teak-masts",
      "type": "technology",
      "name": "Teak Masts",
      "pbgid": 2033749,
      "attribName": "upgrade_naval_teak_masts_abb",
      "age": 3,
      "civs": [
        "ab"
      ],
      "description": "Increase the health of military ships by +10%.",
      "classes": [
        "naval",
        "technology"
      ],
      "displayClasses": [
        "Naval Technology"
      ],
      "unique": true,
      "costs": {
        "food": 0,
        "wood": 75,
        "stone": 0,
        "gold": 125,
        "vizier": 0,
        "oliveoil": 0,
        "total": 200,
        "popcap": 0,
        "time": 20
      },
      "producedBy": [
        "dock"
      ],
      "icon": "https://data.aoe4world.com/images/technologies/teak-masts-2.png",
      "effects": [
        {
          "property": "hitpoints",
          "select": {
            "class": [
              [
                "ship",
                "springald"
              ],
              [
                "ship",
                "archer"
              ],
              [
                "ship",
                "incendiary"
              ],
              [
                "warship"
              ]
            ],
            "id": [
              "galleass",
              "grand-galley"
            ]
          },
          "effect": "multiply",
          "value": 1.1,
          "type": "passive"
        }
      ]
    },
    {
      "id": "teak-masts-2",
      "baseId": "teak-masts",
      "type": "technology",
      "name": "Teak Masts",
      "pbgid": 2033749,
      "attribName": "upgrade_naval_teak_masts_abb",
      "age": 2,
      "civs": [
        "ay"
      ],
      "description": "Increase the health of military ships by +10%.",
      "classes": [
        "naval",
        "technology"
      ],
      "displayClasses": [
        "Naval Technology"
      ],
      "unique": true,
      "costs": {
        "food": 0,
        "wood": 75,
        "stone": 0,
        "gold": 125,
        "vizier": 0,
        "oliveoil": 0,
        "total": 200,
        "popcap": 0,
        "time": 20
      },
      "producedBy": [
        "dock"
      ],
      "icon": "https://data.aoe4world.com/images/technologies/teak-masts-2.png",
      "effects": [
        {
          "property": "hitpoints",
          "select": {
            "class": [
              [
                "ship",
                "springald"
              ],
              [
                "ship",
                "archer"
              ],
              [
                "ship",
                "incendiary"
              ],
              [
                "warship"
              ]
            ],
            "id": [
              "galleass",
              "grand-galley"
            ]
          },
          "effect": "multiply",
          "value": 1.1,
          "type": "passive"
        }
      ]
    }
  ]
}