{
  "__note__": "This is file is autogenerated, do not edit it manually. For more info https://data.aoe4world.com/",
  "__version__": "0.0.2",
  "id": "teutonic-order",
  "name": "Teutonic Order",
  "type": "technology",
  "civs": [
    "kt"
  ],
  "unique": false,
  "displayClasses": [
    "Advance to Age IV"
  ],
  "classes": [
    "abbasid_upgrade",
    "abbasid_wing_upgrade",
    "age_up_upgrade",
    "ayyubid_cmp_upgrade",
    "scar_abbasid_wing_culture",
    "scar_castle_age_upgrade"
  ],
  "minAge": 3,
  "icon": "https://data.aoe4world.com/images/technologies/teutonic-order-3.png",
  "description": "- All gold units gain +2 melee armor.",
  "variations": [
    {
      "id": "teutonic-order-3",
      "baseId": "teutonic-order",
      "type": "technology",
      "name": "Teutonic Order",
      "pbgid": 5000211,
      "attribName": "upgrade_age_castle_com_2_tem",
      "age": 3,
      "civs": [
        "kt"
      ],
      "description": "- All gold units gain +2 melee armor.",
      "classes": [
        "abbasid_upgrade",
        "abbasid_wing_upgrade",
        "age_up_upgrade",
        "ayyubid_cmp_upgrade",
        "scar_abbasid_wing_culture",
        "scar_castle_age_upgrade"
      ],
      "displayClasses": [
        "Advance to Age IV"
      ],
      "unique": false,
      "costs": {
        "food": 2400,
        "wood": 0,
        "stone": 0,
        "gold": 1200,
        "total": 3600,
        "popcap": 0,
        "time": 45
      },
      "producedBy": [
        "capital-town-center",
        "town-center"
      ],
      "icon": "https://data.aoe4world.com/images/technologies/teutonic-order-3.png",
      "effects": [
        {
          "property": "meleeArmor",
          "value": 2,
          "effect": "change",
          "type": "passive"
        }
      ]
    }
  ]
}