{
  "id": "wynguard-rangers-4",
  "baseId": "wynguard-rangers",
  "type": "unit",
  "name": "Wynguard Rangers",
  "pbgid": 2075743,
  "attribName": "unit_wynguard_rangers_eng",
  "age": 4,
  "civs": [
    "en"
  ],
  "description": "Produces an army of 6 Wynguard Rangers.",
  "classes": [
    "mixed",
    "force",
    "army"
  ],
  "displayClasses": [
    "Mixed Force Army"
  ],
  "unique": false,
  "costs": {
    "food": 0,
    "wood": 450,
    "stone": 0,
    "gold": 250,
    "vizier": 0,
    "oliveoil": 0,
    "total": 700,
    "popcap": 6,
    "time": 45
  },
  "producedBy": [
    "wynguard-palace"
  ],
  "icon": "https://data.aoe4world.com/images/units/wynguard-rangers-1.png",
  "weapons": [],
  "armor": [],
  "sight": {
    "line": 0,
    "height": 0
  },
  "movement": {
    "speed": null
  }
}