{
  "id": "upgrade-horseman-4",
  "baseId": "upgrade-horseman-4",
  "type": "upgrade",
  "name": "Elite Horsemen",
  "age": 4,
  "civs": [
    "en",
    "hr",
    "fr",
    "ch",
    "ab",
    "ru"
  ],
  "description": "Upgrade Veteran Horsemen to Elite Horsemen.",
  "classes": [
    "unit",
    "technology",
    "22"
  ],
  "displayClasses": [
    "Unit Technology 2/2"
  ],
  "unique": false,
  "costs": {
    "food": 300,
    "wood": 0,
    "stone": 0,
    "gold": 700,
    "total": 1000,
    "popcap": 0,
    "time": 60
  },
  "producedBy": [
    "stable"
  ],
  "unlocks": "horseman-4",
  "icon": "https://data.aoe4world.com/images/upgrades/horseman-4.png"
}