{
  "id": "mosque-3",
  "baseId": "mosque",
  "type": "building",
  "name": "Mosque",
  "pbgid": 3091240,
  "attribName": "building_unit_religious_control_abb_ha_01",
  "age": 3,
  "civs": [
    "ay"
  ],
  "description": "Produces religious units and houses religious technologies. Starting in the Castle Age (III), religious units can pick up Relics and place them in this building to generate Gold.",
  "classes": [
    "religious",
    "building"
  ],
  "displayClasses": [
    "Religious Building"
  ],
  "unique": false,
  "costs": {
    "food": 0,
    "wood": 200,
    "stone": 0,
    "gold": 0,
    "vizier": 0,
    "oliveoil": 0,
    "total": 200,
    "popcap": 0,
    "time": 25
  },
  "producedBy": [
    "villager"
  ],
  "icon": "https://data.aoe4world.com/images/buildings/mosque-3.png",
  "hitpoints": 2100,
  "weapons": [],
  "armor": [
    {
      "type": "ranged",
      "value": 50
    }
  ],
  "sight": {
    "line": 25,
    "height": 8
  },
  "influences": [
    "Buildings within influence gain +5 Fire Armor.\nStructures built within House of Wisdom influence area help progress to the Golden Age and unlock additional bonuses."
  ]
}