{
  "id": "market-2",
  "baseId": "market",
  "type": "building",
  "name": "Market",
  "pbgid": 129989,
  "attribName": "building_econ_market_mon",
  "age": 2,
  "civs": [
    "mo"
  ],
  "description": "Allows the buying and selling of resources and produces the Trader.",
  "classes": [
    "building",
    "economy_building",
    "exchange",
    "market_keybinding",
    "packable_building",
    "scar_market",
    "siegeable",
    "trade_post"
  ],
  "displayClasses": [
    "Economy Building",
    "Trade Site"
  ],
  "unique": false,
  "costs": {
    "food": 0,
    "wood": 100,
    "stone": 0,
    "gold": 0,
    "vizier": 0,
    "oliveoil": 0,
    "total": 100,
    "popcap": 0,
    "time": 20
  },
  "producedBy": [
    "villager"
  ],
  "icon": "https://data.aoe4world.com/images/buildings/market-2.png",
  "hitpoints": 1000,
  "weapons": [],
  "armor": [
    {
      "type": "ranged",
      "value": 50
    }
  ],
  "sight": {
    "inner_height": 8,
    "inner_radius": 20,
    "outer_height": 0,
    "outer_radius": 25,
    "base": 25,
    "line": 25,
    "height": 8
  },
  "influences": [
    "Buildings within the influence of the Ovoo can spend Stone on improved production items:\n- Unit production produces two units instead of one."
  ]
}