{
  "id": "fortress-2",
  "baseId": "fortress",
  "type": "building",
  "name": "Fortress",
  "pbgid": 5000214,
  "attribName": "building_defense_fortress_tem",
  "age": 2,
  "civs": [
    "kt"
  ],
  "description": "Unique Landmark fortification for the Knights Templar, can be fully destroyed.\nHas an aura that improves nearby units range.\nEach Fortress increases the number of Pilgrims travelling.",
  "classes": [
    "audio_production_landmark",
    "building",
    "castle",
    "defensive_structure",
    "has_default_building_weapons",
    "landmark",
    "military",
    "mortal_landmark",
    "scar_keep",
    "siegeable",
    "templar_fortress",
    "town_bell_target",
    "town_center_or_landmark",
    "wonder"
  ],
  "displayClasses": [
    "Defensive Landmark"
  ],
  "unique": true,
  "costs": {
    "food": 0,
    "wood": 0,
    "stone": 600,
    "gold": 300,
    "vizier": 0,
    "oliveoil": 0,
    "total": 900,
    "popcap": 0,
    "time": 180
  },
  "producedBy": [
    "villager"
  ],
  "icon": "https://data.aoe4world.com/images/buildings/fortress-2.png",
  "hitpoints": 4000,
  "weapons": [
    {
      "name": "Bow",
      "type": "ranged",
      "damage": 12,
      "speed": 0.5,
      "range": {
        "min": 0,
        "max": 8
      },
      "modifiers": [
        {
          "property": "rangedAttack",
          "target": {
            "class": [
              [
                "naval",
                "unit"
              ]
            ]
          },
          "effect": "change",
          "value": 10,
          "type": "passive"
        }
      ],
      "durations": {
        "aim": 0,
        "windup": 0.125,
        "attack": 0.125,
        "winddown": 0,
        "reload": 0.25,
        "setup": 0,
        "teardown": 0,
        "cooldown": 0
      },
      "attribName": "weapon_keep_arrows_a",
      "pbgid": 127372
    },
    {
      "name": "Springald",
      "type": "ranged",
      "damage": 40,
      "speed": 3.875,
      "range": {
        "min": 0,
        "max": 9
      },
      "modifiers": [
        {
          "property": "rangedAttack",
          "target": {
            "class": [
              [
                "naval",
                "unit"
              ]
            ]
          },
          "effect": "change",
          "value": 40,
          "type": "passive"
        }
      ],
      "durations": {
        "aim": 0,
        "windup": 0.25,
        "attack": 0.125,
        "winddown": 0.5,
        "reload": 3,
        "setup": 0,
        "teardown": 0,
        "cooldown": 0
      },
      "attribName": "weapon_keep_springald",
      "pbgid": 127373
    },
    {
      "name": "Trebuchet",
      "type": "siege",
      "damage": 40,
      "speed": 4.875,
      "range": {
        "min": 0,
        "max": 13
      },
      "modifiers": [
        {
          "property": "siegeAttack",
          "target": {
            "class": [
              [
                "building"
              ]
            ]
          },
          "effect": "change",
          "value": 200,
          "type": "passive"
        },
        {
          "property": "siegeAttack",
          "target": {
            "class": [
              [
                "naval",
                "unit"
              ]
            ]
          },
          "effect": "change",
          "value": 200,
          "type": "passive"
        }
      ],
      "durations": {
        "aim": 0,
        "windup": 0.25,
        "attack": 0.125,
        "winddown": 0.5,
        "reload": 4,
        "setup": 0,
        "teardown": 0,
        "cooldown": 0
      },
      "attribName": "weapon_keep_trebuchet",
      "pbgid": 9000153
    },
    {
      "name": "Hot Oil",
      "type": "siege",
      "damage": 30,
      "speed": 9.625,
      "range": {
        "min": 0,
        "max": 1.5
      },
      "modifiers": [],
      "durations": {
        "aim": 0.5,
        "windup": 0,
        "attack": 0.125,
        "winddown": 1,
        "reload": 0,
        "setup": 0,
        "teardown": 0,
        "cooldown": 8
      },
      "attribName": "weapon_keep_murder_hole",
      "pbgid": 145524
    },
    {
      "name": "Bow",
      "type": "ranged",
      "damage": 12,
      "speed": 0.5,
      "range": {
        "min": 0,
        "max": 8
      },
      "modifiers": [
        {
          "property": "rangedAttack",
          "target": {
            "class": [
              [
                "naval",
                "unit"
              ]
            ]
          },
          "effect": "change",
          "value": 10,
          "type": "passive"
        }
      ],
      "durations": {
        "aim": 0,
        "windup": 0.25,
        "attack": 0.125,
        "winddown": 0,
        "reload": 0.125,
        "setup": 0,
        "teardown": 0,
        "cooldown": 0
      },
      "attribName": "weapon_keep_arrows_b",
      "pbgid": 197085
    },
    {
      "name": "Bow",
      "type": "ranged",
      "damage": 12,
      "speed": 0.5,
      "range": {
        "min": 0,
        "max": 8
      },
      "modifiers": [
        {
          "property": "rangedAttack",
          "target": {
            "class": [
              [
                "naval",
                "unit"
              ]
            ]
          },
          "effect": "change",
          "value": 10,
          "type": "passive"
        }
      ],
      "durations": {
        "aim": 0,
        "windup": 0.375,
        "attack": 0.125,
        "winddown": 0,
        "reload": 0,
        "setup": 0,
        "teardown": 0,
        "cooldown": 0
      },
      "attribName": "weapon_keep_arrows_c",
      "pbgid": 197086
    },
    {
      "name": "Bow",
      "type": "ranged",
      "damage": 10,
      "speed": 2.625,
      "range": {
        "min": 0,
        "max": 8
      },
      "modifiers": [
        {
          "property": "rangedAttack",
          "target": {
            "class": [
              [
                "naval",
                "unit"
              ]
            ]
          },
          "effect": "change",
          "value": 10,
          "type": "passive"
        }
      ],
      "durations": {
        "aim": 0.5,
        "windup": 0,
        "attack": 0.125,
        "winddown": 0,
        "reload": 0,
        "setup": 0,
        "teardown": 0,
        "cooldown": 2
      },
      "attribName": "weapon_keep_arrows_garrison",
      "pbgid": 171261
    },
    {
      "name": "Bow",
      "type": "ranged",
      "damage": 10,
      "speed": 2.625,
      "range": {
        "min": 0,
        "max": 8
      },
      "modifiers": [
        {
          "property": "rangedAttack",
          "target": {
            "class": [
              [
                "naval",
                "unit"
              ]
            ]
          },
          "effect": "change",
          "value": 10,
          "type": "passive"
        }
      ],
      "durations": {
        "aim": 0.5,
        "windup": 0,
        "attack": 0.125,
        "winddown": 0,
        "reload": 0,
        "setup": 0,
        "teardown": 0,
        "cooldown": 2
      },
      "attribName": "weapon_keep_arrows_garrison",
      "pbgid": 171261
    },
    {
      "name": "Bow",
      "type": "ranged",
      "damage": 10,
      "speed": 2.625,
      "range": {
        "min": 0,
        "max": 8
      },
      "modifiers": [
        {
          "property": "rangedAttack",
          "target": {
            "class": [
              [
                "naval",
                "unit"
              ]
            ]
          },
          "effect": "change",
          "value": 10,
          "type": "passive"
        }
      ],
      "durations": {
        "aim": 0.5,
        "windup": 0,
        "attack": 0.125,
        "winddown": 0,
        "reload": 0,
        "setup": 0,
        "teardown": 0,
        "cooldown": 2
      },
      "attribName": "weapon_keep_arrows_garrison",
      "pbgid": 171261
    },
    {
      "name": "Bow",
      "type": "ranged",
      "damage": 10,
      "speed": 2.625,
      "range": {
        "min": 0,
        "max": 8
      },
      "modifiers": [
        {
          "property": "rangedAttack",
          "target": {
            "class": [
              [
                "naval",
                "unit"
              ]
            ]
          },
          "effect": "change",
          "value": 10,
          "type": "passive"
        }
      ],
      "durations": {
        "aim": 0.5,
        "windup": 0,
        "attack": 0.125,
        "winddown": 0,
        "reload": 0,
        "setup": 0,
        "teardown": 0,
        "cooldown": 2
      },
      "attribName": "weapon_keep_arrows_garrison",
      "pbgid": 171261
    },
    {
      "name": "Bow",
      "type": "ranged",
      "damage": 10,
      "speed": 2.625,
      "range": {
        "min": 0,
        "max": 8
      },
      "modifiers": [
        {
          "property": "rangedAttack",
          "target": {
            "class": [
              [
                "naval",
                "unit"
              ]
            ]
          },
          "effect": "change",
          "value": 10,
          "type": "passive"
        }
      ],
      "durations": {
        "aim": 0.5,
        "windup": 0,
        "attack": 0.125,
        "winddown": 0,
        "reload": 0,
        "setup": 0,
        "teardown": 0,
        "cooldown": 2
      },
      "attribName": "weapon_keep_arrows_garrison",
      "pbgid": 171261
    },
    {
      "name": "Bow",
      "type": "ranged",
      "damage": 10,
      "speed": 2.625,
      "range": {
        "min": 0,
        "max": 8
      },
      "modifiers": [
        {
          "property": "rangedAttack",
          "target": {
            "class": [
              [
                "naval",
                "unit"
              ]
            ]
          },
          "effect": "change",
          "value": 10,
          "type": "passive"
        }
      ],
      "durations": {
        "aim": 0.5,
        "windup": 0,
        "attack": 0.125,
        "winddown": 0,
        "reload": 0,
        "setup": 0,
        "teardown": 0,
        "cooldown": 2
      },
      "attribName": "weapon_keep_arrows_garrison",
      "pbgid": 171261
    },
    {
      "name": "Bow",
      "type": "ranged",
      "damage": 10,
      "speed": 2.625,
      "range": {
        "min": 0,
        "max": 8
      },
      "modifiers": [
        {
          "property": "rangedAttack",
          "target": {
            "class": [
              [
                "naval",
                "unit"
              ]
            ]
          },
          "effect": "change",
          "value": 10,
          "type": "passive"
        }
      ],
      "durations": {
        "aim": 0.5,
        "windup": 0,
        "attack": 0.125,
        "winddown": 0,
        "reload": 0,
        "setup": 0,
        "teardown": 0,
        "cooldown": 2
      },
      "attribName": "weapon_keep_arrows_garrison",
      "pbgid": 171261
    },
    {
      "name": "Bow",
      "type": "ranged",
      "damage": 10,
      "speed": 2.625,
      "range": {
        "min": 0,
        "max": 8
      },
      "modifiers": [
        {
          "property": "rangedAttack",
          "target": {
            "class": [
              [
                "naval",
                "unit"
              ]
            ]
          },
          "effect": "change",
          "value": 10,
          "type": "passive"
        }
      ],
      "durations": {
        "aim": 0.5,
        "windup": 0,
        "attack": 0.125,
        "winddown": 0,
        "reload": 0,
        "setup": 0,
        "teardown": 0,
        "cooldown": 2
      },
      "attribName": "weapon_keep_arrows_garrison",
      "pbgid": 171261
    },
    {
      "name": "Bow",
      "type": "ranged",
      "damage": 10,
      "speed": 2.625,
      "range": {
        "min": 0,
        "max": 8
      },
      "modifiers": [
        {
          "property": "rangedAttack",
          "target": {
            "class": [
              [
                "naval",
                "unit"
              ]
            ]
          },
          "effect": "change",
          "value": 10,
          "type": "passive"
        }
      ],
      "durations": {
        "aim": 0.5,
        "windup": 0,
        "attack": 0.125,
        "winddown": 0,
        "reload": 0,
        "setup": 0,
        "teardown": 0,
        "cooldown": 2
      },
      "attribName": "weapon_keep_arrows_garrison",
      "pbgid": 171261
    },
    {
      "name": "Bow",
      "type": "ranged",
      "damage": 10,
      "speed": 2.625,
      "range": {
        "min": 0,
        "max": 8
      },
      "modifiers": [
        {
          "property": "rangedAttack",
          "target": {
            "class": [
              [
                "naval",
                "unit"
              ]
            ]
          },
          "effect": "change",
          "value": 10,
          "type": "passive"
        }
      ],
      "durations": {
        "aim": 0.5,
        "windup": 0,
        "attack": 0.125,
        "winddown": 0,
        "reload": 0,
        "setup": 0,
        "teardown": 0,
        "cooldown": 2
      },
      "attribName": "weapon_keep_arrows_garrison",
      "pbgid": 171261
    },
    {
      "name": "Bow",
      "type": "ranged",
      "damage": 10,
      "speed": 2.625,
      "range": {
        "min": 0,
        "max": 8
      },
      "modifiers": [
        {
          "property": "rangedAttack",
          "target": {
            "class": [
              [
                "naval",
                "unit"
              ]
            ]
          },
          "effect": "change",
          "value": 10,
          "type": "passive"
        }
      ],
      "durations": {
        "aim": 0.5,
        "windup": 0,
        "attack": 0.125,
        "winddown": 0,
        "reload": 0,
        "setup": 0,
        "teardown": 0,
        "cooldown": 2
      },
      "attribName": "weapon_keep_arrows_garrison",
      "pbgid": 171261
    },
    {
      "name": "Bow",
      "type": "ranged",
      "damage": 10,
      "speed": 2.625,
      "range": {
        "min": 0,
        "max": 8
      },
      "modifiers": [
        {
          "property": "rangedAttack",
          "target": {
            "class": [
              [
                "naval",
                "unit"
              ]
            ]
          },
          "effect": "change",
          "value": 10,
          "type": "passive"
        }
      ],
      "durations": {
        "aim": 0.5,
        "windup": 0,
        "attack": 0.125,
        "winddown": 0,
        "reload": 0,
        "setup": 0,
        "teardown": 0,
        "cooldown": 2
      },
      "attribName": "weapon_keep_arrows_garrison",
      "pbgid": 171261
    },
    {
      "name": "Bow",
      "type": "ranged",
      "damage": 10,
      "speed": 2.625,
      "range": {
        "min": 0,
        "max": 8
      },
      "modifiers": [
        {
          "property": "rangedAttack",
          "target": {
            "class": [
              [
                "naval",
                "unit"
              ]
            ]
          },
          "effect": "change",
          "value": 10,
          "type": "passive"
        }
      ],
      "durations": {
        "aim": 0.5,
        "windup": 0,
        "attack": 0.125,
        "winddown": 0,
        "reload": 0,
        "setup": 0,
        "teardown": 0,
        "cooldown": 2
      },
      "attribName": "weapon_keep_arrows_garrison",
      "pbgid": 171261
    },
    {
      "name": "Bow",
      "type": "ranged",
      "damage": 10,
      "speed": 2.625,
      "range": {
        "min": 0,
        "max": 8
      },
      "modifiers": [
        {
          "property": "rangedAttack",
          "target": {
            "class": [
              [
                "naval",
                "unit"
              ]
            ]
          },
          "effect": "change",
          "value": 10,
          "type": "passive"
        }
      ],
      "durations": {
        "aim": 0.5,
        "windup": 0,
        "attack": 0.125,
        "winddown": 0,
        "reload": 0,
        "setup": 0,
        "teardown": 0,
        "cooldown": 2
      },
      "attribName": "weapon_keep_arrows_garrison",
      "pbgid": 171261
    },
    {
      "name": "Bow",
      "type": "ranged",
      "damage": 10,
      "speed": 2.625,
      "range": {
        "min": 0,
        "max": 8
      },
      "modifiers": [
        {
          "property": "rangedAttack",
          "target": {
            "class": [
              [
                "naval",
                "unit"
              ]
            ]
          },
          "effect": "change",
          "value": 10,
          "type": "passive"
        }
      ],
      "durations": {
        "aim": 0.5,
        "windup": 0,
        "attack": 0.125,
        "winddown": 0,
        "reload": 0,
        "setup": 0,
        "teardown": 0,
        "cooldown": 2
      },
      "attribName": "weapon_keep_arrows_garrison",
      "pbgid": 171261
    },
    {
      "name": "Bow",
      "type": "ranged",
      "damage": 10,
      "speed": 2.625,
      "range": {
        "min": 0,
        "max": 8
      },
      "modifiers": [
        {
          "property": "rangedAttack",
          "target": {
            "class": [
              [
                "naval",
                "unit"
              ]
            ]
          },
          "effect": "change",
          "value": 10,
          "type": "passive"
        }
      ],
      "durations": {
        "aim": 0.5,
        "windup": 0,
        "attack": 0.125,
        "winddown": 0,
        "reload": 0,
        "setup": 0,
        "teardown": 0,
        "cooldown": 2
      },
      "attribName": "weapon_keep_arrows_garrison",
      "pbgid": 171261
    },
    {
      "name": "Bow",
      "type": "ranged",
      "damage": 10,
      "speed": 2.625,
      "range": {
        "min": 0,
        "max": 8
      },
      "modifiers": [
        {
          "property": "rangedAttack",
          "target": {
            "class": [
              [
                "naval",
                "unit"
              ]
            ]
          },
          "effect": "change",
          "value": 10,
          "type": "passive"
        }
      ],
      "durations": {
        "aim": 0.5,
        "windup": 0,
        "attack": 0.125,
        "winddown": 0,
        "reload": 0,
        "setup": 0,
        "teardown": 0,
        "cooldown": 2
      },
      "attribName": "weapon_keep_arrows_garrison",
      "pbgid": 171261
    },
    {
      "name": "Bow",
      "type": "ranged",
      "damage": 10,
      "speed": 2.625,
      "range": {
        "min": 0,
        "max": 8
      },
      "modifiers": [
        {
          "property": "rangedAttack",
          "target": {
            "class": [
              [
                "naval",
                "unit"
              ]
            ]
          },
          "effect": "change",
          "value": 10,
          "type": "passive"
        }
      ],
      "durations": {
        "aim": 0.5,
        "windup": 0,
        "attack": 0.125,
        "winddown": 0,
        "reload": 0,
        "setup": 0,
        "teardown": 0,
        "cooldown": 2
      },
      "attribName": "weapon_keep_arrows_garrison",
      "pbgid": 171261
    },
    {
      "name": "Bow",
      "type": "ranged",
      "damage": 10,
      "speed": 2.625,
      "range": {
        "min": 0,
        "max": 8
      },
      "modifiers": [
        {
          "property": "rangedAttack",
          "target": {
            "class": [
              [
                "naval",
                "unit"
              ]
            ]
          },
          "effect": "change",
          "value": 10,
          "type": "passive"
        }
      ],
      "durations": {
        "aim": 0.5,
        "windup": 0,
        "attack": 0.125,
        "winddown": 0,
        "reload": 0,
        "setup": 0,
        "teardown": 0,
        "cooldown": 2
      },
      "attribName": "weapon_keep_arrows_garrison",
      "pbgid": 171261
    },
    {
      "name": "Bow",
      "type": "ranged",
      "damage": 10,
      "speed": 2.625,
      "range": {
        "min": 0,
        "max": 8
      },
      "modifiers": [
        {
          "property": "rangedAttack",
          "target": {
            "class": [
              [
                "naval",
                "unit"
              ]
            ]
          },
          "effect": "change",
          "value": 10,
          "type": "passive"
        }
      ],
      "durations": {
        "aim": 0.5,
        "windup": 0,
        "attack": 0.125,
        "winddown": 0,
        "reload": 0,
        "setup": 0,
        "teardown": 0,
        "cooldown": 2
      },
      "attribName": "weapon_keep_arrows_garrison",
      "pbgid": 171261
    },
    {
      "name": "Arbalest",
      "type": "ranged",
      "damage": 40,
      "speed": 1.5,
      "range": {
        "min": 0,
        "max": 9.5
      },
      "modifiers": [
        {
          "property": "rangedAttack",
          "target": {
            "class": [
              [
                "naval",
                "unit"
              ]
            ]
          },
          "effect": "change",
          "value": 50,
          "type": "passive"
        }
      ],
      "durations": {
        "aim": 0.125,
        "windup": 0.25,
        "attack": 0.125,
        "winddown": 0,
        "reload": 1,
        "setup": 0,
        "teardown": 0,
        "cooldown": 0
      },
      "attribName": "weapon_keep_arbalest_d",
      "pbgid": 2149899
    }
  ],
  "armor": [
    {
      "type": "ranged",
      "value": 50
    },
    {
      "type": "fire",
      "value": 6
    }
  ],
  "sight": {
    "inner_height": 501,
    "inner_radius": 57,
    "outer_height": -15,
    "outer_radius": 58,
    "base": 57.97093023255814,
    "line": 58,
    "height": 501
  },
  "garrison": {
    "capacity": 15,
    "classes": [
      "infantry",
      "villager",
      "infantry ranged",
      "monk",
      "cavalry",
      "khan"
    ]
  },
  "influences": [
    "The Templar Headquarters and Fortresses grant Stone Walls in influence +25% health and an arrowslit emplacement."
  ]
}