{
  "id": "veteran-spearmen-3",
  "baseId": "veteran-spearmen",
  "type": "upgrade",
  "name": "Upgrade to Veteran",
  "pbgid": 124662,
  "attribName": "upgrade_unit_spearman_3",
  "age": 3,
  "civs": [
    "ab"
  ],
  "description": "Upgrade Hardened Spearmen to Veteran Spearmen.",
  "classes": [
    "unit",
    "technology",
    "2/3"
  ],
  "displayClasses": [
    "Unit Technology 2/3"
  ],
  "unique": false,
  "costs": {
    "food": 100,
    "wood": 0,
    "stone": 0,
    "gold": 250,
    "vizier": 0,
    "oliveoil": 0,
    "total": 350,
    "popcap": 0,
    "time": 60
  },
  "producedBy": [
    "barracks"
  ],
  "icon": "https://data.aoe4world.com/images/upgrades/veteran-spearmen-3.png",
  "unlocks": ""
}