{
  "__note__": "This is file is autogenerated, do not edit it manually. For more info https://data.aoe4world.com/",
  "__version__": "0.0.2",
  "id": "battering-ram",
  "name": "Battering Ram",
  "type": "unit",
  "civs": [
    "ab",
    "en",
    "hr",
    "fr",
    "ch",
    "de",
    "mo",
    "ru"
  ],
  "unique": false,
  "displayClasses": [
    "Siege"
  ],
  "classes": [
    "siege"
  ],
  "minAge": 1,
  "icon": "https://data.aoe4world.com/images/units/battering-ram.png",
  "description": "Durable infantry transport effective against buildings and walls.\n+ High ranged armor\n+ High health\n- Can only attack buildings\n- Slow movement speed",
  "variations": [
    {
      "id": "battering-ram-1",
      "baseId": "battering-ram",
      "type": "unit",
      "name": "Battering Ram",
      "age": 1,
      "civs": [
        "ab"
      ],
      "description": "Durable infantry transport effective against buildings and walls.\n+ High ranged armor\n+ High health\n- Can only attack buildings\n- Slow movement speed",
      "classes": [
        "siege"
      ],
      "displayClasses": [
        "Siege"
      ],
      "unique": true,
      "costs": {
        "food": 0,
        "wood": 300,
        "stone": 0,
        "gold": 0,
        "total": 300,
        "popcap": 1,
        "time": 80
      },
      "producedBy": [
        "infantry-units"
      ],
      "hitpoints": 700,
      "weapons": [
        {
          "type": "siege",
          "damage": 200,
          "speed": 5,
          "range": {
            "min": 0,
            "max": 0.3
          }
        }
      ],
      "armor": [
        {
          "type": "ranged",
          "value": 30
        }
      ],
      "sight": {
        "line": 30,
        "height": 10
      },
      "movement": {
        "speed": 0.75
      },
      "icon": "https://data.aoe4world.com/images/units/battering-ram.png"
    },
    {
      "id": "battering-ram-2",
      "baseId": "battering-ram",
      "type": "unit",
      "name": "Battering Ram",
      "age": 2,
      "civs": [
        "en",
        "hr",
        "fr",
        "ch",
        "de",
        "mo",
        "ru"
      ],
      "description": "Durable infantry transport effective against buildings and walls.\n+ High ranged armor\n+ High health\n- Can only attack buildings\n- Slow movement speed",
      "classes": [
        "siege"
      ],
      "displayClasses": [
        "Siege"
      ],
      "unique": false,
      "costs": {
        "food": 0,
        "wood": 300,
        "stone": 0,
        "gold": 0,
        "total": 300,
        "popcap": 1,
        "time": 80
      },
      "producedBy": [
        "infantry-units"
      ],
      "hitpoints": 700,
      "weapons": [
        {
          "type": "siege",
          "damage": 200,
          "speed": 5,
          "range": {
            "min": 0,
            "max": 0.3
          }
        }
      ],
      "armor": [
        {
          "type": "ranged",
          "value": 30
        }
      ],
      "sight": {
        "line": 30,
        "height": 10
      },
      "movement": {
        "speed": 0.75
      },
      "icon": "https://data.aoe4world.com/images/units/battering-ram-2.png"
    }
  ]
}