{
  "id": "battering-ram-2",
  "baseId": "battering-ram",
  "name": "Battering Ram",
  "age": 2,
  "civs": [
    "en",
    "hr",
    "fr",
    "ch",
    "de",
    "mo",
    "ru"
  ],
  "description": "Durable infantry transport effective against buildings and walls.\n\n+ High ranged armor\n\n+ High health\n\n- Can only attack buildings\n\n- Slow movement speed",
  "class": "Siege",
  "classes": [
    "Siege"
  ],
  "unique": false,
  "hitpoints": 700,
  "movement": {
    "speed": 0.75
  },
  "costs": {
    "food": 0,
    "wood": 300,
    "stone": 0,
    "gold": 0,
    "total": 300,
    "popcap": 1,
    "time": 80
  },
  "attack": {
    "melee": 0,
    "ranged": 0,
    "siege": 200,
    "fire": 0,
    "speed": 5,
    "dps": 40
  },
  "range": {
    "min": 0,
    "max": 0.3
  },
  "vision": {
    "lineOfSight": 30,
    "heightOfSight": 10
  },
  "armor": {
    "melee": 0,
    "ranged": 30,
    "fire": 0
  },
  "producedBy": [
    "infantry-units"
  ],
  "icon": "https://data.aoe4world.com/images/units/battering-ram-2.png"
}