{
  "id": "fishing-boat-2",
  "baseId": "fishing-boat",
  "type": "unit",
  "name": "Fishing Boat",
  "pbgid": 6922142,
  "attribName": "unit_naval_fishing_boat_2_hre_ha_01",
  "age": 2,
  "civs": [
    "od"
  ],
  "description": "Small boat that gathers Food from either Deep Water Fish or Shoreline Fish. Drops off gathered resources at the Dock.\n+ Can repair\n- No combat",
  "classes": [
    "worker",
    "ship"
  ],
  "displayClasses": [
    "Worker",
    "Ship"
  ],
  "unique": false,
  "costs": {
    "food": 0,
    "wood": 75,
    "stone": 0,
    "gold": 0,
    "vizier": 0,
    "oliveoil": 0,
    "total": 75,
    "popcap": 1,
    "time": 25
  },
  "producedBy": [
    "dock"
  ],
  "icon": "https://data.aoe4world.com/images/units/fishing-boat-2.png",
  "hitpoints": 100,
  "weapons": [],
  "armor": [],
  "sight": {
    "line": 44,
    "height": 501
  },
  "movement": {
    "speed": 1.5
  }
}