{
  "id": "gilded-man-at-arms-4",
  "baseId": "gilded-man-at-arms",
  "type": "unit",
  "name": "Elite Gilded Man-at-Arms",
  "pbgid": 4252958,
  "attribName": "unit_manatarms_4_hre_ha_01",
  "age": 4,
  "civs": [
    "od"
  ],
  "description": "Tough infantry with good damage.\n+ High armor\n- Slow movement\n- Countered by Knights, Lancers, and Crossbowmen",
  "classes": [
    "heavy",
    "melee",
    "infantry"
  ],
  "displayClasses": [
    "Heavy Melee Infantry"
  ],
  "unique": true,
  "costs": {
    "food": 200,
    "wood": 0,
    "stone": 0,
    "gold": 40,
    "vizier": 0,
    "oliveoil": 0,
    "total": 240,
    "popcap": 2,
    "time": 27
  },
  "producedBy": [
    "barracks",
    "burgrave-palace"
  ],
  "icon": "https://data.aoe4world.com/images/units/gilded-man-at-arms-4.png",
  "hitpoints": 340,
  "weapons": [
    {
      "name": "Sword",
      "type": "melee",
      "damage": 21,
      "speed": 1.125,
      "range": {
        "min": 0,
        "max": 0.295
      },
      "modifiers": [],
      "durations": {
        "aim": 0,
        "windup": 0.5,
        "attack": 0.125,
        "winddown": 0.5,
        "reload": 0,
        "setup": 0,
        "teardown": 0,
        "cooldown": 0
      },
      "attribName": "weapon_manatarms_4_hre_ha_01",
      "pbgid": 2127019
    },
    {
      "name": "Ax",
      "type": "melee",
      "damage": 22,
      "speed": 1.125,
      "range": {
        "min": 0,
        "max": 0.295
      },
      "modifiers": [],
      "durations": {
        "aim": 0,
        "windup": 0.5,
        "attack": 0.125,
        "winddown": 0.5,
        "reload": 0,
        "setup": 0,
        "teardown": 0,
        "cooldown": 0
      },
      "attribName": "weapon_manatarms_4_2handaxe_hre_ha_01",
      "pbgid": 2127023
    },
    {
      "name": "Bludgeon",
      "type": "melee",
      "damage": 22,
      "speed": 1.125,
      "range": {
        "min": 0,
        "max": 0.295
      },
      "modifiers": [
        {
          "property": "meleeAttack",
          "target": {
            "class": [
              [
                "heavy"
              ]
            ]
          },
          "effect": "change",
          "value": 6,
          "type": "passive"
        }
      ],
      "durations": {
        "aim": 0,
        "windup": 0.5,
        "attack": 0.125,
        "winddown": 0.5,
        "reload": 0,
        "setup": 0,
        "teardown": 0,
        "cooldown": 0
      },
      "attribName": "weapon_manatarms_4_2handmace_hre_ha_01",
      "pbgid": 2127025
    },
    {
      "name": "Torch",
      "type": "fire",
      "damage": 18,
      "speed": 2.125,
      "range": {
        "min": 0,
        "max": 1.25
      },
      "modifiers": [],
      "durations": {
        "aim": 0,
        "windup": 0.75,
        "attack": 0.125,
        "winddown": 0,
        "reload": 0,
        "setup": 0,
        "teardown": 0,
        "cooldown": 1.25
      },
      "attribName": "weapon_torch_hre_ha_01",
      "pbgid": 2126943
    }
  ],
  "armor": [
    {
      "type": "melee",
      "value": 5
    },
    {
      "type": "ranged",
      "value": 5
    }
  ],
  "sight": {
    "line": 36,
    "height": 10
  },
  "movement": {
    "speed": 1.125
  }
}